algomojo/__init__.py
algomojo/pyapi.py
algomojo-1.4.dist-info/METADATA
algomojo-1.4.dist-info/WHEEL
algomojo-1.4.dist-info/top_level.txt
algomojo-1.4.dist-info/RECORD
