Metadata-Version: 2.1
Name: algomojo
Version: 1.4
Summary: Algomojo - Arrow API Python Client V1
Home-page: https://algomojo.com/docs/
Author: Algomojo
Author-email: support@algomojo.com
License: MIT
Classifier: License :: OSI Approved :: MIT License
Classifier: Programming Language :: Python
Classifier: Programming Language :: Python :: 2
Classifier: Programming Language :: Python :: 3
Requires-Dist: requests
